{"info":{"file":"src/offset.js","fileShort":"src/offset.js","fileSafe":"src_offset_js","link":"files/src_offset_js/index.html"},"complexity":{"methodAggregate":{"cyclomatic":32,"cyclomaticDensity":28.829,"halstead":{"bugs":1.61,"difficulty":41.986,"effort":202822.535,"length":689,"time":11267.919,"vocabulary":129,"volume":4830.736,"operands":{"distinct":106,"total":387,"identifiers":["__stripped__"]},"operators":{"distinct":23,"total":302,"identifiers":["__stripped__"]}},"params":24,"sloc":{"logical":111,"physical":232}},"settings":{"commonjs":true,"forin":false,"logicalor":true,"switchcase":true,"trycatch":false,"newmi":true},"classes":[],"dependencies":[],"errors":[],"lineEnd":232,"lineStart":1,"maintainability":62.826,"methods":[{"cyclomatic":1,"cyclomaticDensity":7.692,"halstead":{"bugs":0.105,"difficulty":6,"effort":1890,"length":63,"time":105,"vocabulary":32,"volume":315,"operands":{"distinct":24,"total":36,"identifiers":["__stripped__"]},"operators":{"distinct":8,"total":27,"identifiers":["__stripped__"]}},"params":8,"sloc":{"logical":13,"physical":219},"errors":[],"lineEnd":232,"lineStart":14,"name":"<anonymous>"},{"cyclomatic":3,"cyclomaticDensity":300,"halstead":{"bugs":0.022,"difficulty":5,"effort":322.647,"length":18,"time":17.925,"vocabulary":12,"volume":64.529,"operands":{"distinct":6,"total":10,"identifiers":["__stripped__"]},"operators":{"distinct":6,"total":8,"identifiers":["__stripped__"]}},"params":1,"sloc":{"logical":1,"physical":3},"errors":[],"lineEnd":23,"lineStart":21,"name":"getWindow"},{"cyclomatic":11,"cyclomaticDensity":33.333,"halstead":{"bugs":0.361,"difficulty":23.135,"effort":25045.564,"length":189,"time":1391.42,"vocabulary":53,"volume":1082.577,"operands":{"distinct":37,"total":107,"identifiers":["__stripped__"]},"operators":{"distinct":16,"total":82,"identifiers":["__stripped__"]}},"params":3,"sloc":{"logical":33,"physical":49},"errors":[],"lineEnd":74,"lineStart":26,"name":"<anonymous>"},{"cyclomatic":7,"cyclomaticDensity":31.818,"halstead":{"bugs":0.189,"difficulty":15.865,"effort":9009.96,"length":106,"time":500.553,"vocabulary":41,"volume":567.901,"operands":{"distinct":26,"total":55,"identifiers":["__stripped__"]},"operators":{"distinct":15,"total":51,"identifiers":["__stripped__"]}},"params":1,"sloc":{"logical":22,"physical":42},"errors":[],"lineEnd":119,"lineStart":78,"name":"<anonymous>"},{"cyclomatic":1,"cyclomaticDensity":100,"halstead":{"bugs":0.01,"difficulty":1.167,"effort":35,"length":10,"time":1.944,"vocabulary":8,"volume":30,"operands":{"distinct":6,"total":7,"identifiers":["__stripped__"]},"operators":{"distinct":2,"total":3,"identifiers":["__stripped__"]}},"params":1,"sloc":{"logical":1,"physical":3},"errors":[],"lineEnd":86,"lineStart":84,"name":"<anonymous>"},{"cyclomatic":4,"cyclomaticDensity":19.048,"halstead":{"bugs":0.229,"difficulty":23.725,"effort":16276.242,"length":136,"time":904.236,"vocabulary":33,"volume":686.038,"operands":{"distinct":20,"total":73,"identifiers":["__stripped__"]},"operators":{"distinct":13,"total":63,"identifiers":["__stripped__"]}},"params":0,"sloc":{"logical":21,"physical":40},"errors":[],"lineEnd":160,"lineStart":121,"name":"<anonymous>"},{"cyclomatic":1,"cyclomaticDensity":100,"halstead":{"bugs":0.007,"difficulty":2,"effort":39.303,"length":7,"time":2.183,"vocabulary":7,"volume":19.651,"operands":{"distinct":3,"total":3,"identifiers":["__stripped__"]},"operators":{"distinct":4,"total":4,"identifiers":["__stripped__"]}},"params":0,"sloc":{"logical":1,"physical":11},"errors":[],"lineEnd":182,"lineStart":172,"name":"<anonymous>"},{"cyclomatic":4,"cyclomaticDensity":100,"halstead":{"bugs":0.035,"difficulty":9,"effort":936,"length":26,"time":52,"vocabulary":16,"volume":104,"operands":{"distinct":7,"total":14,"identifiers":["__stripped__"]},"operators":{"distinct":9,"total":12,"identifiers":["__stripped__"]}},"params":0,"sloc":{"logical":4,"physical":9},"errors":[],"lineEnd":181,"lineStart":173,"name":"<anonymous>"},{"cyclomatic":1,"cyclomaticDensity":50,"halstead":{"bugs":0.019,"difficulty":3.214,"effort":184.37,"length":16,"time":10.243,"vocabulary":12,"volume":57.359,"operands":{"distinct":7,"total":9,"identifiers":["__stripped__"]},"operators":{"distinct":5,"total":7,"identifiers":["__stripped__"]}},"params":2,"sloc":{"logical":2,"physical":23},"errors":[],"lineEnd":208,"lineStart":186,"name":"<anonymous>"},{"cyclomatic":1,"cyclomaticDensity":100,"halstead":{"bugs":0.014,"difficulty":2.286,"effort":94.887,"length":12,"time":5.272,"vocabulary":11,"volume":41.513,"operands":{"distinct":7,"total":8,"identifiers":["__stripped__"]},"operators":{"distinct":4,"total":4,"identifiers":["__stripped__"]}},"params":1,"sloc":{"logical":1,"physical":19},"errors":[],"lineEnd":207,"lineStart":189,"name":"<anonymous>"},{"cyclomatic":6,"cyclomaticDensity":85.714,"halstead":{"bugs":0.069,"difficulty":12.273,"effort":2533.569,"length":47,"time":140.754,"vocabulary":21,"volume":206.439,"operands":{"distinct":11,"total":27,"identifiers":["__stripped__"]},"operators":{"distinct":10,"total":20,"identifiers":["__stripped__"]}},"params":3,"sloc":{"logical":7,"physical":17},"errors":[],"lineEnd":206,"lineStart":190,"name":"<anonymous>"},{"cyclomatic":1,"cyclomaticDensity":100,"halstead":{"bugs":0.018,"difficulty":2.25,"effort":120.992,"length":15,"time":6.722,"vocabulary":12,"volume":53.774,"operands":{"distinct":8,"total":9,"identifiers":["__stripped__"]},"operators":{"distinct":4,"total":6,"identifiers":["__stripped__"]}},"params":2,"sloc":{"logical":1,"physical":14},"errors":[],"lineEnd":229,"lineStart":216,"name":"<anonymous>"},{"cyclomatic":3,"cyclomaticDensity":100,"halstead":{"bugs":0.037,"difficulty":6.222,"effort":696.889,"length":28,"time":38.716,"vocabulary":16,"volume":112,"operands":{"distinct":9,"total":16,"identifiers":["__stripped__"]},"operators":{"distinct":7,"total":12,"identifiers":["__stripped__"]}},"params":2,"sloc":{"logical":3,"physical":10},"errors":[],"lineEnd":227,"lineStart":218,"name":"<anonymous>"}],"methodAverage":{"cyclomatic":3.385,"cyclomaticDensity":86.739,"halstead":{"bugs":0.086,"difficulty":8.626,"effort":4398.879,"length":51.769,"time":244.382,"vocabulary":21.077,"volume":256.983,"operands":{"distinct":13.154,"total":28.769},"operators":{"distinct":7.923,"total":23}},"params":1.846,"sloc":{"logical":8.462,"physical":35.308}},"module":"src/offset.js"},"jshint":{"messages":[{"severity":"error","line":61,"column":26,"message":"Use '!==' to compare with 'null'.","source":"Use '{a}' to compare with '{b}'."},{"severity":"error","line":64,"column":27,"message":"Use '!==' to compare with 'null'.","source":"Use '{a}' to compare with '{b}'."}]},"date":"2016-08-02T22:16:55.000Z"}